{
    "ar": "استكشاف الصهريج للحصول على أدلة.",
    "bg": "Изследвай резервоара за улики.",
    "cs": "Prozkoumejte cisternu pro stopy.",
    "da": "Udforsk cisternen for spor.",
    "de": "Erkunden Sie die Zisterne nach Hinweisen.",
    "el": "Εξερευνήστε τη δεξαμενή για ενδείξεις.",
    "en": "Explore the cistern for clues.",
    "es": "Explora la cisterna en busca de pistas.",
    "es-419": "Explora la cisterna en busca de pistas.",
    "fi": "Tutki vesisäiliötä johtolankojen löytämiseksi.",
    "fr": "Explorez la citerne à la recherche d’indices.",
    "hu": "Fedezze fel a ciszterna a nyomokat.",
    "it": "Esplora la cisterna alla ricerca di indizi.",
    "ja": "手がかりを得るための水槽を探索してください。",
    "ko": "단서를 위해 물통을 탐험해 보세요.",
    "nl": "Verken de stortbak voor aanwijzingen.",
    "nb": "Utforsk sisternen for ledetråder.",
    "pl": "Zbadaj cysterna, aby uzyskać wskazówki.",
    "pt": "Explore a cisterna à procura de pistas.",
    "pt-BR": "Explore a cisterna em busca de pistas.",
    "ro": "Explorează cisterna pentru indicii.",
    "ru": "Исследуйте цистерну для подсказки.",
    "sv": "Utforska cisternen för ledtrådar.",
    "th": "สํารวจความโง่ของเบาะแส",
    "tr": "İpuçları için sarnıç keşfedin.",
    "uk": "Дослідіть цистерну для доказів.",
    "vi": "Khám phá các Cistern cho manh mối.",
    "zh-CN": "探索蓄水池寻找线索。",
    "zh-TW": "探索蓄水池尋找線索。"
}
