{
    "ar": "Mummy Priest",
    "bg": "Mummy Priest",
    "cs": "Mummy Priest",
    "da": "Mummy Priest",
    "de": "Mummy Priest",
    "el": "Mummy Priest",
    "en": "Mummy Priest",
    "es": "Mummy Priest",
    "es-419": "Mummy Priest",
    "fi": "Mummy Priest",
    "fr": "Mummy Priest",
    "hu": "Mummy Priest",
    "it": "Mummy Priest",
    "ja": "Mummy Priest",
    "ko": "Mummy Priest",
    "nl": "Mummy Priest",
    "no": "Mummy Priest",
    "pl": "Mummy Priest",
    "pt": "Mummy Priest",
    "pt-BR": "Mummy Priest",
    "ro": "Mummy Priest",
    "ru": "Mummy Priest",
    "sv": "Mummy Priest",
    "th": "Mummy Priest",
    "tr": "Mummy Priest",
    "uk": "Mummy Priest",
    "vi": "Mummy Priest",
    "zh-CN": "Mummy Priest",
    "zh-TW": "Mummy Priest"
}
