{
    "ar": "الارنب",
    "bg": "Зайче",
    "cs": "Králíček",
    "da": "Bunny",
    "de": "Häschen",
    "el": "Κουνελάκι",
    "en": "Bunny",
    "es": "Conejito",
    "es-419": "Conejito",
    "fi": "Pupu",
    "fr": "Lapin",
    "hu": "Nyuszi",
    "it": "Coniglietta",
    "ja": "バニー",
    "ko": "토끼",
    "nl": "Konijntje",
    "nb": "Bunny",
    "pl": "Króliczek",
    "pt": "Coelho",
    "pt-BR": "Coelhinho",
    "ro": "Iepuraș",
    "ru": "Кролик",
    "sv": "Kanin",
    "th": "กระต่าย",
    "tr": "Tavşan",
    "uk": "Кролик",
    "vi": "Bunny",
    "zh-CN": "兔子",
    "zh-TW": "兔子"
}
