{
    "ar": "mul %s1, %s2",
    "bg": "mul %s1, %s2",
    "cs": "mul %s1, %s2",
    "da": "mul %s1, %s2",
    "de": "mul %s1, %s2",
    "el": "mul %s1, %s2",
    "en": "mul %s1, %s2",
    "es": "mul %s1, %s2",
    "es-419": "mul %s1, %s2",
    "fi": "mul %s1, %s2",
    "fr": "mul %s1, %s2",
    "hu": "mul %s1, %s2",
    "it": "mul %s1, %s2",
    "ja": "mul %s1, %s2",
    "ko": "mul %s1, %s2",
    "nl": "mul %s1, %s2",
    "no": "mul %s1, %s2",
    "pl": "mul %s1, %s2",
    "pt": "mul %s1, %s2",
    "pt-BR": "mul %s1, %s2",
    "ro": "mul %s1, %s2",
    "ru": "mul %s1, %s2",
    "sv": "mul %s1, %s2",
    "th": "mul %s1, %s2",
    "tr": "mul %s1, %s2",
    "uk": "mul %s1, %s2",
    "vi": "mul %s1, %s2",
    "zh-CN": "mul %s1, %s2",
    "zh-TW": "mul %s1, %s2"
}
