{
    "ar": "لقد فعلتها!",
    "bg": "Ти успя!",
    "cs": "Dokázal jsi to!",
    "da": "Du gjorde det!",
    "de": "Du hast es geschafft!",
    "el": "Τα κατάφερες!",
    "en": "You made it!",
    "es": "¡Lo hiciste!",
    "es-419": "¡Lo hiciste!",
    "fi": "Sinä teit sen!",
    "fr": "Tu l'as fait!",
    "hu": "Megcsináltad!",
    "it": "L'hai fatta!",
    "ja": "やった！",
    "ko": "네가 해냈어!",
    "nl": "Je hebt het gehaald!",
    "no": "Du klarte det!",
    "pl": "Zrobiłeś to!",
    "pt": "Você conseguiu!",
    "pt-BR": "Você conseguiu!",
    "ro": "Ai făcut!",
    "ru": "Ты сделал это!",
    "sv": "Du gjorde det!",
    "th": "คุณทำมัน!",
    "tr": "Başardın!",
    "uk": "Ти це зробив!",
    "vi": "Bạn đã thực hiện nó!",
    "zh-CN": "你做到了！",
    "zh-TW": "你做到了！"
}
