{
    "ar": "جزرة",
    "bg": "морков",
    "cs": "Mrkev",
    "da": "Gulerod",
    "de": "Karotte",
    "el": "Καρότο",
    "en": "Carrot",
    "es": "Zanahoria",
    "es-419": "Zanahoria",
    "fi": "Porkkana",
    "fr": "Carotte",
    "hu": "Sárgarépa",
    "it": "Carota",
    "ja": "にんじん",
    "ko": "당근",
    "nl": "Wortel",
    "no": "Gulrot",
    "pl": "Marchewka",
    "pt": "Cenoura",
    "pt-BR": "Cenoura",
    "ro": "Morcov",
    "ru": "Морковь",
    "sv": "Morot",
    "th": "แครอท",
    "tr": "Havuç",
    "uk": "Морква",
    "vi": "Cà rốt",
    "zh-CN": "胡萝卜",
    "zh-TW": "胡蘿蔔"
}
