{
    "ar": "نهاب",
    "bg": "мародер",
    "cs": "Marauder",
    "da": "Marauder",
    "de": "Marodeur",
    "el": "Αρπαγας",
    "en": "Marauder",
    "es": "Merodeador",
    "es-419": "Merodeador",
    "fi": "Rosvo",
    "fr": "Maraudeur",
    "hu": "Martalóc",
    "it": "predone",
    "ja": "マローダー",
    "ko": "약탈자",
    "nl": "Stroper",
    "no": "Marauder",
    "pl": "Maruder",
    "pt": "Marauder",
    "pt-BR": "Marauder",
    "ro": "Jefuitor",
    "ru": "мародер",
    "sv": "Marodör",
    "th": "โจรปล้นสะดม",
    "tr": "çapulcu",
    "uk": "Мародер",
    "vi": "Marauder",
    "zh-CN": "掠夺者",
    "zh-TW": "掠奪者"
}
