{
    "ar": "FLIP2",
    "bg": "FLIP2",
    "cs": "FLIP2",
    "da": "FLIP2",
    "de": "FLIP2",
    "el": "FLIP2",
    "en": "FLIP2",
    "es": "FLIP2",
    "es-419": "FLIP2",
    "fi": "FLIP2",
    "fr": "FLIP2",
    "hu": "FLIP2",
    "it": "FLIP2",
    "ja": "FLIP2",
    "ko": "FLIP2",
    "nl": "FLIP2",
    "no": "FLIP2",
    "pl": "FLIP2",
    "pt": "FLIP2",
    "pt-BR": "FLIP2",
    "ro": "FLIP2",
    "ru": "FLIP2",
    "sv": "FLIP2",
    "th": "FLIP2",
    "tr": "FLIP2",
    "uk": "FLIP2",
    "vi": "FLIP2",
    "zh-CN": "FLIP2",
    "zh-TW": "FLIP2"
}
