{
    "ar": "هذا كل النفوس! دعنا نعود إلى %s1.",
    "bg": "Това са всички души! Да се върнем към %s1.",
    "cs": "To jsou všechny duše! Vraťme se k %s1.",
    "da": "Det er alle sjælene! Lad os vende tilbage til %s1.",
    "de": "Das sind alle Seelen! Kehren wir zu %s1 zurück.",
    "el": "Αυτές είναι όλες οι ψυχές! Ας επιστρέψουμε στο %s1.",
    "en": "That's all of the souls! Let's return to %s1.",
    "es": "¡Eso es todas las almas! Volvamos a %s1.",
    "es-419": "¡Eso es todas las almas! Volvamos a %s1.",
    "fi": "Se on kaikki sielut! Palataan kohtaan %s1.",
    "fr": "C’est toutes les âmes! Revenons à %s1.",
    "hu": "Ez az összes lélek! Térjünk vissza a %s1 elemhez.",
    "it": "Queste sono tutte le anime! Torniamo a %s1.",
    "ja": "それがすべての魂です!%s1に戻りましょう。",
    "ko": "그것이 모든 영혼입니다! %s1로 돌아가 보겠습니다.",
    "nl": "Dat zijn alle zielen! Laten we terugkeren naar %s1.",
    "no": "Det er alle sjelene! La oss gå tilbake til %s1.",
    "pl": "To wszystkie dusze! Wróćmy do %s1.",
    "pt": "Isso é tudo das almas! Voltemos a %s1.",
    "pt-BR": "Isso é tudo das almas! Voltemos a %s1.",
    "ro": "Acestea sunt toate sufletele! Să revenim la %s1.",
    "ru": "Вот и все души! Вернемся к %s1.",
    "sv": "Det är alla själar! Låt oss återgå till %s1.",
    "th": "นั่นคือจิตวิญญาณทั้งหมด! ลองกลับไปที่ %s1",
    "tr": "Tüm ruhlar bu kadar! %s1'e dönelim.",
    "uk": "Ось і всі душі! Повернемося до %s1.",
    "vi": "Đó là tất cả các linh hồn! Hãy quay lại %s1.",
    "zh-CN": "这就是所有的灵魂！让我们返回到 %s1。",
    "zh-TW": "這就是所有的靈魂！讓我們返回到 %s1。"
}
