{
    "ar": "Aspen",
    "bg": "Aspen",
    "cs": "Aspen",
    "da": "Aspen",
    "de": "Aspen",
    "el": "Aspen",
    "en": "Aspen",
    "es": "Aspen",
    "es-419": "Aspen",
    "fi": "Aspen",
    "fr": "Aspen",
    "hu": "Aspen",
    "it": "Aspen",
    "ja": "Aspen",
    "ko": "Aspen",
    "nl": "Aspen",
    "no": "Aspen",
    "pl": "Aspen",
    "pt": "Aspen",
    "pt-BR": "Aspen",
    "ro": "Aspen",
    "ru": "Aspen",
    "sv": "Aspen",
    "th": "Aspen",
    "tr": "Aspen",
    "uk": "Aspen",
    "vi": "Aspen",
    "zh-CN": "Aspen",
    "zh-TW": "Aspen"
}
