{
    "ar": "اختيار الهدف",
    "bg": "Изберете цел",
    "cs": "Vyberte cíl",
    "da": "Vælg et mål",
    "de": "Wählen Sie ein Ziel",
    "el": "Επιλέξτε έναν στόχο",
    "en": "Choose a target",
    "es": "Elige un objetivo",
    "es-419": "Elige un objetivo",
    "fi": "Valitse kohde",
    "fr": "Choisissez une cible",
    "hu": "Válasszon egy célt",
    "it": "Scegli un obiettivo",
    "ja": "ターゲットを選択してください",
    "ko": "대상을 선택하십시오",
    "nl": "Kies een doelwit",
    "no": "Velg et mål",
    "pl": "Wybierz cel",
    "pt": "Escolha um alvo",
    "pt-BR": "Escolha um alvo",
    "ro": "Alegeți o țintă",
    "ru": "Выберите цель",
    "sv": "Välj ett mål",
    "th": "เลือกเป้าหมาย",
    "tr": "Bir hedef seçin",
    "uk": "Виберіть ціль",
    "vi": "Chọn một mục tiêu",
    "zh-CN": "选择一个目标",
    "zh-TW": "選擇一個目標"
}
