{
    "ar": "تصنيف غير صالح",
    "bg": "Невалиден етикет",
    "cs": "Neplatná jmenovka",
    "da": "Ugyldig etiket",
    "de": "Ungültige Bezeichnung",
    "el": "Μη έγκυρη ετικέτα",
    "en": "Invalid label",
    "es": "Etiqueta inválida",
    "es-419": "Etiqueta inválida",
    "fi": "Virheellinen etiketti",
    "fr": "Étiquette invalide",
    "hu": "Érvénytelen címke",
    "it": "Etichetta non valida",
    "ja": "無効なラベル",
    "ko": "라벨이 잘못되었습니다.",
    "nl": "Ongeldig label",
    "no": "Ugyldig etikett",
    "pl": "Nieprawidłowa etykieta",
    "pt": "Rótulo inválido",
    "pt-BR": "Rótulo inválido",
    "ro": "Etichetă nevalidă",
    "ru": "Неверный ярлык",
    "sv": "Ogiltig etikett",
    "th": "ป้ายกำกับไม่ถูกต้อง",
    "tr": "Geçersiz etiket",
    "uk": "Недійсна мітка",
    "vi": "Nhãn không hợp lệ",
    "zh-CN": "标签无效",
    "zh-TW": "標籤無效"
}
