{
    "ar": ".؜بالطبع سنفعل ذلك",
    "bg": "Разбира се, че ще го направим.",
    "cs": "Samozřejmě, že budeme.",
    "da": "Selvfølgelig vil vi det.",
    "de": "Natürlich werden wir das tun.",
    "el": "Φυσικά και θα το κάνουμε.",
    "en": "Of course we will.",
    "es": "Por supuesto que lo haremos.",
    "es-419": "Por supuesto que lo haremos.",
    "fi": "Tietenkin teemme niin.",
    "fr": "Bien sûr que nous le ferons.",
    "hu": "Természetesen megtesszük.",
    "it": "Certo che lo faremo.",
    "ja": "もちろん、私たちはそうします。",
    "ko": "물론 우리는 할 것입니다.",
    "nl": "Natuurlijk zullen we dat doen.",
    "no": "Selvsagt gjør vi det.",
    "pl": "Oczywiście, że tak.",
    "pt": "Claro que sim.",
    "pt-BR": "Claro que vamos.",
    "ro": "Bineînțeles că o vom face.",
    "ru": "Конечно, будем.",
    "sv": "Självklart kommer vi att göra det.",
    "th": "แน่นอนเราจะ.",
    "tr": "Tabii ki yapacağız.",
    "uk": "Звичайно, будемо.",
    "vi": "Tất nhiên chúng tôi sẽ làm.",
    "zh-CN": "我们当然会。",
    "zh-TW": "我們當然會。"
}
