{
    "ar": "سيف نحاسي",
    "bg": "Меден меч",
    "cs": "Měděný meč",
    "da": "Kobbersværd",
    "de": "Kupferschwert",
    "el": "Ξίφος ξίφος",
    "en": "Copper sword",
    "es": "Espada de cobre",
    "es-419": "Espada de cobre",
    "fi": "Kupari miekka",
    "fr": "Épée de cuivre",
    "hu": "Réz kard",
    "it": "Spada di rame",
    "ja": "銅の剣",
    "ko": "구리도",
    "nl": "Koperen zwaard",
    "no": "Kobbersverd",
    "pl": "Miedziany miecz",
    "pt": "Espada de cobre",
    "pt-BR": "Espada de cobre",
    "ro": "Sabia de cupru",
    "ru": "Медный меч",
    "sv": "Kopparsvärd",
    "th": "ดาบทองแดง",
    "tr": "Bakır kılıç",
    "uk": "Мідний меч",
    "vi": "Kiếm đồng",
    "zh-CN": "铜剑",
    "zh-TW": "銅劍"
}
