{
    "ar": "Ogre",
    "bg": "Ogre",
    "cs": "Ogre",
    "da": "Ogre",
    "de": "Ogre",
    "el": "Ogre",
    "en": "Ogre",
    "es": "Ogre",
    "es-419": "Ogre",
    "fi": "Ogre",
    "fr": "Ogre",
    "hu": "Ogre",
    "it": "Ogre",
    "ja": "Ogre",
    "ko": "Ogre",
    "nl": "Ogre",
    "no": "Ogre",
    "pl": "Ogre",
    "pt": "Ogre",
    "pt-BR": "Ogre",
    "ro": "Ogre",
    "ru": "Ogre",
    "sv": "Ogre",
    "th": "Ogre",
    "tr": "Ogre",
    "uk": "Ogre",
    "vi": "Ogre",
    "zh-CN": "Ogre",
    "zh-TW": "Ogre"
}
