{
    "ar": "Agnes",
    "bg": "Agnes",
    "cs": "Agnes",
    "da": "Agnes",
    "de": "Agnes",
    "el": "Agnes",
    "en": "Agnes",
    "es": "Agnes",
    "es-419": "Agnes",
    "fi": "Agnes",
    "fr": "Agnes",
    "hu": "Agnes",
    "it": "Agnes",
    "ja": "Agnes",
    "ko": "Agnes",
    "nl": "Agnes",
    "no": "Agnes",
    "pl": "Agnes",
    "pt": "Agnes",
    "pt-BR": "Agnes",
    "ro": "Agnes",
    "ru": "Agnes",
    "sv": "Agnes",
    "th": "Agnes",
    "tr": "Agnes",
    "uk": "Agnes",
    "vi": "Agnes",
    "zh-CN": "Agnes",
    "zh-TW": "Agnes"
}
