{
    "ar": "بعد توصيل البراغي ، افتح الشفرات.",
    "bg": "След като болтовете са свързани, отключете шифъра.",
    "cs": "Po připojení šroubů odblokujte šifru.",
    "da": "Når boltene er tilsluttet, skal du låse chifteren.",
    "de": "Entriegeln Sie die Chiffre, nachdem die Schrauben angeschlossen wurden.",
    "el": "Αφού συνδεθούν τα μπουλόνια, ξεκλειδώστε τον κρυπτογράφο.",
    "en": "After the bolts are connected, unlock the cipher.",
    "es": "Después de conectar los tornillos, desbloquee el cifrado.",
    "es-419": "Después de conectar los tornillos, desbloquee el cifrado.",
    "fi": "Kun pultit on kytketty, avaa salaus.",
    "fr": "Une fois les boulons connectés, déverrouillez le chiffrement.",
    "hu": "A csavarok csatlakoztatása után oldja fel a rejtjelet.",
    "it": "Dopo aver collegato i bulloni, sbloccare la cifra.",
    "ja": "ボルトを接続したら、暗号を解除します。",
    "ko": "볼트가 연결된 후 암호를 잠금 해제하십시오.",
    "nl": "Nadat de bouten zijn aangesloten, ontgrendelt u het cijfer.",
    "no": "Når boltene er koblet til, låser du chifferen.",
    "pl": "Po podłączeniu śrub odblokuj szyfr.",
    "pt": "Depois que os parafusos estiverem conectados, desbloqueie a cifra.",
    "pt-BR": "Depois que os parafusos estiverem conectados, desbloqueie a cifra.",
    "ro": "După ce șuruburile sunt conectate, deblocați cifrul.",
    "ru": "После того, как болты соединены, разблокируйте шифр.",
    "sv": "När bultarna är anslutna låser du chifferet.",
    "th": "หลังจากเชื่อมต่อสลักเกลียวแล้วให้ปลดล็อครหัสลับ",
    "tr": "Cıvatalar bağlandıktan sonra şifrenin kilidini açın.",
    "uk": "Після підключення болтів розблокуйте шифр.",
    "vi": "Sau khi các bu lông được kết nối, mở khóa mật mã.",
    "zh-CN": "连接螺栓后，解锁密码。",
    "zh-TW": "連接螺栓後，解鎖密碼。"
}
