{
    "ar": "لا تنسى أن تجهيز أسلحة جديدة والدروع!",
    "bg": "Не забравяйте да оборудвате нови оръжия и брони!",
    "cs": "Nezapomeňte vybavit nové zbraně a brnění!",
    "da": "Glem ikke at udstyre nye våben og rustninger!",
    "de": "Vergessen Sie nicht, neue Waffen und Rüstungen auszurüsten!",
    "el": "Μην ξεχάσετε να εξοπλίσει νέα όπλα και πανοπλία!",
    "en": "Do not forget to equip new weapons and armor!",
    "es": "¡No te olvides de equipar nuevas armas y armaduras!",
    "es-419": "¡No te olvides de equipar nuevas armas y armaduras!",
    "fi": "Älä unohda varustaa uusia aseita ja haarniska!",
    "fr": "N’oubliez pas d’équiper de nouvelles armes et armures!",
    "hu": "Ne felejtsük el, hogy felkészítse az új fegyverek és páncélok!",
    "it": "Non dimenticate di equipaggiare nuove armi e armature!",
    "ja": "新しい武器や鎧を装備することを忘れないでください!",
    "ko": "새로운 무기와 갑옷을 장착하는 것을 잊지 마세요!",
    "nl": "Vergeet niet om nieuwe wapens en armor uit te rusten!",
    "nb": "Ikke glem å utstyre nye våpen og rustninger!",
    "pl": "Nie zapomnij wyposażyć nowe bronie i zbroi!",
    "pt": "Não se esqueça de equipar novas armas e armaduras!",
    "pt-BR": "Não se esqueça de equipar novas armas e armaduras!",
    "ro": "Nu uitați să dota arme noi și armuri!",
    "ru": "Не забудьте оборудовать новое оружие и броню!",
    "sv": "Glöm inte att utrusta nya vapen och rustningar!",
    "th": "อย่าลืมที่จะจัดอาวุธใหม่และเกราะ!",
    "tr": "Yeni silah ve zırh donatmak unutmayın!",
    "uk": "Не забудьте обладнати нову зброю і броню!",
    "vi": "Đừng quên trang bị vũ khí và áo giáp mới!",
    "zh-CN": "别忘了装备新的武器和盔甲！",
    "zh-TW": "別忘了裝備新的武器和盔甲!"
}
