{
    "ar": "زمرد",
    "bg": "смарагд",
    "cs": "Smaragd",
    "da": "smaragd",
    "de": "Smaragd",
    "el": "σμαράγδι",
    "en": "Emerald",
    "es": "Esmeralda",
    "es-419": "Esmeralda",
    "fi": "Smaragdi",
    "fr": "émeraude",
    "hu": "Smaragd",
    "it": "Smeraldo",
    "ja": "エメラルド",
    "ko": "에메랄드",
    "nl": "Smaragd",
    "no": "smaragd",
    "pl": "Szmaragd",
    "pt": "Esmeralda",
    "pt-BR": "Esmeralda",
    "ro": "Smarald",
    "ru": "Изумруд",
    "sv": "Smaragd",
    "th": "มรกต",
    "tr": "Zümrüt",
    "uk": "Смарагдовий",
    "vi": "Ngọc lục bảo",
    "zh-CN": "翠",
    "zh-TW": "翠"
}
